[
    {
        "id": "17effdac-9de5-4877-85d6-54ee3179dce5",
        "data": {
            "answer": "A",
            "options": [
                "Hold a session with the stakeholders to introduce agility - explaining the business value of prioritization, accountability, and improved quality from frequent reviews.",
                "Conduct a cost benefit analysis for the new project comparing predictive and agile approaches and present it to the stakeholders.",
                "Invite the stakeholders to a backlog grooming session so that they understand the scope of work and the development approach.",
                "Send the stakeholders video links explaining agile approaches as well as supporting case studies from the industry."
            ],
            "question": "A project manager works for an organization that uses the predictive method of project management. The project manager has completed training for agile project management and begins to manage projects using the agile method. Stakeholders are not familiar with agile and are having difficulty understanding the new project methodology. How should the project manager address this issue?",
            "num_answers": 4
        },
        "name": "PMP Mini Test 06 - 01",
        "type": "mcq",
        "image": null,
        "question_tags_count": 0
    },
    {
        "id": "37079c64-744e-44c9-b41b-772b579805e6",
        "data": {
            "answer": "B",
            "options": [
                "Size of the activity",
                "Value of the activity to stakeholders",
                "Cost of the activity",
                "Ease of completion of the activity"
            ],
            "question": "An agile team is determining which activities to complete first during an upcoming project iteration for a new product development. Which factor should they use to rank the order of activities that will be delivered?",
            "num_answers": 4
        },
        "name": "PMP Mini Test 06 - 02",
        "type": "mcq",
        "image": null,
        "question_tags_count": 0
    },
    {
        "id": "48cc205b-8a2d-4605-bd0e-cab053944ef9",
        "data": {
            "answer": "B",
            "options": ["Agile", "Hybrid", "Predictive", "Waterfall"],
            "question": "A project team is brainstorming the best project management methodology to recommend to senior management for adoption. The project team's idea is characterized by frequent requirement changes, incremental and iterative changes, customer focus, and defined stages with specific documents produced to meet industry regulatory standards. Which project management methodology is preferred in this case?",
            "num_answers": 4
        },
        "name": "PMP Mini Test 06 - 03",
        "type": "mcq",
        "image": null,
        "question_tags_count": 0
    },
    {
        "id": "f5cfc12e-75a5-4e05-86c8-9620cd9ded4f",
        "data": {
            "answer": "B",
            "options": ["Traditional", "Agile", "Waterfall", "Iterative"],
            "question": "A project team has adopted a new project management methodology which entails holding regular review and retrospective meetings every two weeks. In addition, there are daily status meetings and whiteboards are the main tool used to document decisions and action points. Which project management methodology has the team adopted?",
            "num_answers": 4
        },
        "name": "PMP Mini Test 06 - 04",
        "type": "mcq",
        "image": null,
        "question_tags_count": 0
    },
    {
        "id": "d4fe2643-1100-4517-9378-713255af4225",
        "data": {
            "answer": "A",
            "options": ["Ideation 2.0", "Scrum", "Kanban", "Hybrid"],
            "question": "What methodology uses new approaches to implement solutions to problems that are encountered daily?",
            "num_answers": 4
        },
        "name": "PMP Mini Test 06 - 05",
        "type": "mcq",
        "image": null,
        "question_tags_count": 0
    },
    {
        "id": "b35c9eca-016d-43c3-8813-a8ba1e4a6dba",
        "data": {
            "answer": "A",
            "options": [
                "Good cost value and poor schedule value",
                "Poor cost value and good schedule value",
                "Good cost value and good schedule value",
                "Poor cost value and poor schedule value"
            ],
            "question": "During a project performance evaluation meeting, a team established that the performance of the project as of the status date was as follows: schedule performance index (SPI) = 0.5; cost performance index (CPI) = 1.5. The client had identified cost and schedule performance as key in terms of value. Based on these performance figures, which of the following describes the value being delivered to the client as of the status date?",
            "num_answers": 4
        },
        "name": "PMP Mini Test 06 - 06",
        "type": "mcq",
        "image": null,
        "question_tags_count": 0
    },
    {
        "id": "bac7e96b-6ab3-4632-bd69-9a04cc6393b5",
        "data": {
            "answer": "B",
            "options": [
                "Leverage budget reserves to add vendors familiar with the regulations to the project team.",
                "Conduct an analysis of how incorporating agile methodologies will impact the project.",
                "Present this request to the PMO and the project sponsor.",
                "Implement the request and train the project team on agile methodologies."
            ],
            "question": "A project management office (PMO) normally runs projects using the waterfall approach. A project currently in development is impacted by local regulations which are being updated regularly. The project team feels that implementing agile techniques would benefit the project due to the constantly changing regulations. What should the project manager do in this scenario?",
            "num_answers": 4
        },
        "name": "PMP Mini Test 06 - 07",
        "type": "mcq",
        "image": null,
        "question_tags_count": 0
    },
    {
        "id": "d378f403-00e5-4827-b5c9-7b3a873bae7e",
        "data": {
            "answer": "A",
            "options": [
                "Escalate the project risk to a higher level.",
                "Meet with the project sponsor to redefine project benefits.",
                "Inform the stakeholders of the need to develop a contingency plan.",
                "Submit a change request to the change control board (CCB)."
            ],
            "question": "A local government provides subsidies for healthcare activities. An organization plans to leverage this subsidy for a project to provide health testing services for at-risk populations. After the project has started, the government announces that this testing service might not qualify for the subsidy. What should the project manager do?",
            "num_answers": 4
        },
        "name": "PMP Mini Test 06 - 08",
        "type": "mcq",
        "image": null,
        "question_tags_count": 0
    },
    {
        "id": "fa7480d7-e93b-40b9-bbd1-d7f0d23d2721",
        "data": {
            "answer": "D",
            "options": [
                "Projects are used to develop new products, processes, or services.",
                "Projects are used to modify existing products, processes, or services.",
                "Projects are used to deliver day-to-day activities, processes, or services.",
                "Projects are used to develop and modify products, processes, or services."
            ],
            "question": "A project manager is part of a project management strategy focus group that is brainstorming the ways projects will be used to add business value to the organization in the upcoming quarter. Which statement(s) describes broadly how organizations use projects to add business value?",
            "num_answers": 4
        },
        "name": "PMP Mini Test 06 - 09",
        "type": "mcq",
        "image": null,
        "question_tags_count": 0
    },
    {
        "id": "45968d63-de87-4e9c-9005-05808645e88d",
        "data": {
            "answer": "D",
            "options": [
                "Project sponsor",
                "Project management office (PMO) director",
                "Chief executive officer (CEO)",
                "Steering committee"
            ],
            "question": "A megaproject had reached 10% completion when there was a sudden change of company ownership. After being put on hold for a few years, the project is now under study to resume. Who is responsible for approving the updated budget, assigning key resources and relaunching the project?",
            "num_answers": 4
        },
        "name": "PMP Mini Test 06 - 10",
        "type": "mcq",
        "image": null,
        "question_tags_count": 0
    },
    {
        "id": "c6de3b0e-cfdb-4361-8295-cccac24d71bb",
        "data": {
            "answer": "D",
            "options": [
                "Meet with the other stakeholders to discuss the project objectives.",
                "Review the assumption log.",
                "Update the stakeholder engagement plan.",
                "Refer to the benefits management plan."
            ],
            "question": "Due to regulatory changes, a government agency is now a key stakeholder in a complex project. An agency representative has asked the project manager to explain how well the advantages derived from the project align with the agency's business strategies. What should the project manager do?",
            "num_answers": 4
        },
        "name": "PMP Mini Test 06 - 11",
        "type": "mcq",
        "image": null,
        "question_tags_count": 0
    },
    {
        "id": "cfc66a27-d9e5-4547-9d19-3a54059b33a0",
        "data": {
            "answer": "C",
            "options": [
                "Terminate the contract with the client and return the advance payment immediately.",
                "Proceed with the project as planned and try to resolve the challenges within the existing budget and schedule.",
                "Notify the client and request a change order to increase the project budget and extend the project schedule.",
                "Attempt to resolve the technical challenges using existing resources, even if this means sacrificing quality."
            ],
            "question": "A project manager has been awarded a firm-fixed-price (FFP) contract to develop a new mobile app for a client. The contract scope is well-defined and the client has approved the project plan. However, during the course of the project, the team encountered some unexpected technical challenges. These challenges will require additional time and resources to resolve. Which of the following is the most suitable course of action to take?",
            "num_answers": 4
        },
        "name": "PMP Mini Test 06 - 12",
        "type": "mcq",
        "image": null,
        "question_tags_count": 0
    },
    {
        "id": "789b696e-36be-42ff-8721-ae1b05be9c3e",
        "data": {
            "answer": "A",
            "options": [
                "Hold a session with the stakeholders explaining the business value of prioritization, mindset, accountability, and improved quality.",
                "Conduct a cost benefit analysis for the new project comparing predictive and agile approaches and present it to the stakeholders.",
                "Invite the stakeholders to a backlog grooming session so that they understand the scope of work and the development approach.",
                "Send the stakeholders video links explaining agile approaches as well as supporting case studies from the industry."
            ],
            "question": "A project manager in a predictive environment has recently completed agile training and is starting to manage projects in an agile fashion. The organization is new to agile and not everyone understands the principles. How should the project manager gain support going forward?",
            "num_answers": 4
        },
        "name": "PMP Mini Test 06 - 13",
        "type": "mcq",
        "image": null,
        "question_tags_count": 0
    },
    {
        "id": "75bd3dd0-3378-4cb9-9855-3a56a59c6f86",
        "data": {
            "answer": "D",
            "options": [
                "Work breakdown structure",
                "Project management plan",
                "Project scope statement",
                "Business case"
            ],
            "question": "A project manager is midway through project delivery. The project manager decides to hold a stakeholder engagement meeting with senior management and the clients to examine if the project deliverables are achieving business value. Which of the documents contains critical information to help the project manager with this?",
            "num_answers": 4
        },
        "name": "PMP Mini Test 06 - 14",
        "type": "mcq",
        "image": null,
        "question_tags_count": 0
    },
    {
        "id": "807885d0-d403-44f2-a0f6-db42b20679a4",
        "data": {
            "answer": "A",
            "options": [
                "Measurable objectives of critical success factors",
                "Detailed description and requirements of the final deliverable",
                "Work breakdown structure (WBS)",
                "Performance measurement baseline"
            ],
            "question": "A project manager has been assigned to a new project. During the initial review of the project charter, the project manager reaches out to the project sponsor to discuss important information that is missing in the document. What piece of information is appropriate for the project manager to request?",
            "num_answers": 4
        },
        "name": "PMP Mini Test 06 - 15",
        "type": "mcq",
        "image": null,
        "question_tags_count": 0
    },
    {
        "id": "d6c505bc-3417-4124-a5c3-62834572bd03",
        "data": {
            "answer": "A",
            "options": [
                "Update the resource management plan and record the necessary skills in the issues log.",
                "Engage with stakeholders to find a qualified replacement for the external resource.",
                "Initiate training for an internal resource on the required skills and assign the remaining tasks.",
                "Revise the project's schedule and budget estimates and submit a change request."
            ],
            "question": "A project is currently halfway through its timeline when one of the external resources becomes unexpectedly unavailable for the rest of the project. This unavailability puts the project's successful completion within budget and on time at risk. What should the project manager do as the initial step in addressing this?",
            "num_answers": 4
        },
        "name": "PMP Mini Test 06 - 16",
        "type": "mcq",
        "image": null,
        "question_tags_count": 0
    },
    {
        "id": "e8bccf42-cf20-47c8-8439-37468cfc939d",
        "data": {
            "answer": "C",
            "options": [
                "Use a predictive approach and send the daily status report to the customer.",
                "Use an Agile approach and showcase each successful completion of the story.",
                "Use a hybrid approach and showcase each successful completion of each module.",
                "Use a predictive approach and showcase each successful completion of each module."
            ],
            "question": "The project manager's company won a digital transformation project request for proposal (RFP) with clear scope, time and cost. As part of the RFP clause, the project manager's company also provided the number of resources required to complete the project. This is a very high investment project, and the customer wants to monitor the progress regularly. Since it is a fixed price project, what approach should the project manager use?",
            "num_answers": 4
        },
        "name": "PMP Mini Test 06 - 17",
        "type": "mcq",
        "image": null,
        "question_tags_count": 0
    },
    {
        "id": "35adf158-926a-48ad-8215-6c45750fef1e",
        "data": {
            "answer": "C",
            "options": [
                "Replace remote project team members with co-located team members.",
                "Assign tasks of lower priority to the remote team members.",
                "Leverage online meeting platforms for the standups and consider the working hours of remote team members when scheduling.",
                "Use some of the project budget to provide training on agile methods for all remote team members."
            ],
            "question": "A global organization that has always used predictive project management is now moving towards agile project management. In the first agile project of the organization, members from remote teams are failing to attend the daily standup meetings. How can the project manager resolve this issue?",
            "num_answers": 4
        },
        "name": "PMP Mini Test 06 - 18",
        "type": "mcq",
        "image": null,
        "question_tags_count": 0
    },
    {
        "id": "b9d8759e-463a-4b4a-9141-5b1b2a1539ec",
        "data": {
            "answer": "C",
            "options": [
                "Categorize the conflict as \"interpersonal\" and direct the team members to handle it themselves.",
                "Publicly discuss the conflict during the next daily standup to encourage open communication.",
                "Schedule a private one-on-one meeting with each team member to understand their perspective.",
                "Add the conflict to the shared project backlog and prioritize its resolution alongside other tasks."
            ],
            "question": "A project manager notices a potential conflict between a remote developer and an on-site tester during a sprint; the developer feels the tester is being overly critical of their code, while the tester is concerned about potential bugs impacting the release schedule. What should the project manager do first?",
            "num_answers": 4
        },
        "name": "PMP Mini Test 06 - 19",
        "type": "mcq",
        "image": null,
        "question_tags_count": 0
    },
    {
        "id": "f89bd192-b08b-49d8-b8dc-b04eb9d394cb",
        "data": {
            "answer": "C",
            "options": [
                "Take control of the decision-making process.",
                "Provide the team with a detailed process for making decisions.",
                "Support the team’s choices and project decisions.",
                "Train the project team on decision-making techniques."
            ],
            "question": "A project is in progress and the project plan follows waterfall but deliverables are incrementally given to the customer in an agile manner. The project team is comfortable with the hybrid approach and has successfully made important decisions for previous projects.",
            "num_answers": 4
        },
        "name": "PMP Mini Test 06 - 20",
        "type": "mcq",
        "image": null,
        "question_tags_count": 0
    },
    {
        "id": "b43d524f-37c9-4032-915e-2170f7fdfe45",
        "data": {
            "answer": "C",
            "options": [
                "At the next team standup, ask the team why the stakeholder is upset.",
                "Update the scope and project plan to meet the stakeholder’s requests.",
                "Communicate with both the stakeholder and the product owner to foster project alignment.",
                "Meet individually with the stakeholder to review the project backlog."
            ],
            "question": "A stakeholder that is not experienced with agile has emailed the project team expressing frustration and displeasure with their work. In the email, the stakeholder is demanding significant changes in both the project scope and deliverables. How should the project manager address this situation?",
            "num_answers": 4
        },
        "name": "PMP Mini Test 06 - 21",
        "type": "mcq",
        "image": null,
        "question_tags_count": 0
    },
    {
        "id": "2c990d6f-1e97-4059-9f4d-45fff5287c0c",
        "data": {
            "answer": "B",
            "options": [
                "To define the scope",
                "To resolve conflict",
                "To minimise the cost",
                "To reduce the delivery time"
            ],
            "question": "A project manager is assigned to a project with a lot of stakeholders and competing priorities. What will be the main objective to initiate and conduct negotiations?",
            "num_answers": 4
        },
        "name": "PMP Mini Test 06 - 22",
        "type": "mcq",
        "image": null,
        "question_tags_count": 0
    },
    {
        "id": "dc3c6504-08bc-4c91-a4ed-0a19a6bd2b7e",
        "data": {
            "answer": "D",
            "options": [
                "Email the customer weekly updates including the project risk register and notes from daily standups.",
                "Document a detailed summary of the project along with a list of stakeholders, and send it to the customer monthly.",
                "Schedule daily meetings to provide a brief project summary and details on what the project team is currently working on.",
                "Schedule weekly meetings with the customer to present incremental project updates and to have the customer validate project progress."
            ],
            "question": "A project manager is on a project with a very involved customer. The customer demands regular updates on the project, including the current project status and planned next steps. What is the best way to communicate with the customer?",
            "num_answers": 4
        },
        "name": "PMP Mini Test 06 - 23",
        "type": "mcq",
        "image": null,
        "question_tags_count": 0
    },
    {
        "id": "2d9cd8f8-cd96-46b0-be74-7b1a1f58eb4e",
        "data": {
            "answer": "A",
            "options": [
                "Work closely with the marketing team to promote the product and adapt to market changes.",
                "Ensure that the project has sufficient budget and resources to address any challenges.",
                "Be actively involved in the project by monitoring progress, making necessary changes, and capturing data.",
                "Invite the stakeholders to attend all standups to ensure they are actively involved in the project’s success."
            ],
            "question": "An organization is launching a new product that is critical to the company's success. The stakeholders have identified three key factors for success: market adaptation, rapid response to market offerings, and agility. What should the project manager do to ensure the project's success?",
            "num_answers": 4
        },
        "name": "PMP Mini Test 06 - 24",
        "type": "mcq",
        "image": null,
        "question_tags_count": 0
    },
    {
        "id": "2faee4f2-eb79-4c00-873f-03906a62d8a9",
        "data": {
            "answer": "B",
            "options": [
                "Use a hybrid approach, integrating predictive labeling work streams into an agile roll-out schedule.",
                "Use a hybrid approach, integrating an agile labeling workflow into a predictive roll-out schedule.",
                "Apply agile planning to both the manufacturing and labeling work streams to align the workflows.",
                "Apply predictive planning to the labeling work stream and streamline the change control process."
            ],
            "question": "A project manager is planning a worldwide product launch. Manufacturing the product is subject to rigid time constraints related to the production line and raw material availability. There are also uncertainties around regional labeling regulations that are expected to evolve within the launch period. How can the project manager integrate planning and development for the unknown labeling requirements?",
            "num_answers": 4
        },
        "name": "PMP Mini Test 06 - 25",
        "type": "mcq",
        "image": null,
        "question_tags_count": 0
    },
    {
        "id": "240c890c-df75-4b0c-89e5-8858e122da2a",
        "data": {
            "answer": "C",
            "options": [
                "Consult with their functional manager.",
                "Accept the risk and move on.",
                "Update the project risk register.",
                "Assess the risk in a workshop."
            ],
            "question": "A project manager is assigned to a new environmental project. When reviewing a vendor's proposal, the project manager identifies a technical risk that will have an impact on the project manager's company's operational cost. What should the project manager do first?",
            "num_answers": 4
        },
        "name": "PMP Mini Test 06 - 26",
        "type": "mcq",
        "image": null,
        "question_tags_count": 0
    },
    {
        "id": "5efb024e-ee27-49ca-b684-0349ea027f61",
        "data": {
            "answer": "C",
            "options": [
                "Inform the sponsor that the project has ended explaining the reason for the project termination.",
                "Leveraging notes from the meeting, work with the project team to improve the deliverables.",
                "Meet with the stakeholders to identify how to address the identified issues and how to proceed with the project.",
                "Document the concerns presented and send them to the change control board (CCB) for guidance on how to proceed."
            ],
            "question": "During a meeting with stakeholders, the project manager received multiple concerns about the quality of the project’s deliverables. The customer feels so strongly about these concerns that they decide they will not approve any future deliverables. What should the project manager do in this scenario?",
            "num_answers": 4
        },
        "name": "PMP Mini Test 06 - 27",
        "type": "mcq",
        "image": null,
        "question_tags_count": 0
    },
    {
        "id": "b55fd242-e607-4f61-82fd-97ff61fa356c",
        "data": {
            "answer": "A",
            "options": [
                "Use asynchronous communication tools.",
                "Schedule two meetings that accommodate most.",
                "Rotate the meeting time on a weekly basis.",
                "Meet with team members in the same time zone."
            ],
            "question": "A project manager for a cross-functional team is finding it difficult to schedule regular meetings and communicate with all team members and stakeholders due to various time zones. What should the project manager do?",
            "num_answers": 4
        },
        "name": "PMP Mini Test 06 - 28",
        "type": "mcq",
        "image": null,
        "question_tags_count": 0
    },
    {
        "id": "8af0ff8d-bf9b-4fac-a433-7018561f4b21",
        "data": {
            "answer": "C",
            "options": [
                "Prioritize, record, publish, communicate and address",
                "Record, publish, communicate, prioritize and address",
                "Record, prioritize, publish, address and communicate",
                "Prioritize, record, publish, address and communicate"
            ],
            "question": "A project manager is a part of a project that is using the Scrum framework. The project manager needs to monitor the impediments log and facilitate the resolution of impediments raised by the team. What is the correct order of the five steps used to manage the impediments log?",
            "num_answers": 4
        },
        "name": "PMP Mini Test 06 - 29",
        "type": "mcq",
        "image": null,
        "question_tags_count": 0
    },
    {
        "id": "753f5c51-a94f-46d0-b2ed-69af7a7e0f25",
        "data": {
            "answer": "C",
            "options": [
                "Finish project delivery with the predictive methodology.",
                "Extend the project timeline to accommodate the change.",
                "Reevaluate project scope and prioritize critical tasks.",
                "Request a complete overhaul of the project plan."
            ],
            "question": "A project manager is halfway through a project using a predictive methodology when the organization announces a transition to a hybrid approach. The project sponsor instructs the team to transition to this new hybrid approach immediately, even though the team has no prior experience with hybrid projects. What is the best course of action for the project manager to take?",
            "num_answers": 4
        },
        "name": "PMP Mini Test 06 - 30",
        "type": "mcq",
        "image": null,
        "question_tags_count": 0
    }
]
